{
  "users": [
    {
      "id": "user1",
      "account": "Tom",
      "password": "Tom123",
      "token": "",
      "lastLoginTime": ""
    },
    {
      "id": "user2",
      "account": "May",
      "password": "May999",
      "token": "",
      "lastLoginTime": ""
    }
  ],
  "bookmarks": {
    "user1": [
      {
        "bookmarksId": 1,
        "title": "前端三大框架比較",
        "url": "http://前端三大框架比較.com.tw",
        "tags": ["React", "Vue"]
      },
      {
        "bookmarksId": 2,
        "title": "如何開始學React",
        "url": "http://如何開始學React.com.tw",
        "tags": ["React", "ES6"]
      }
    ],
    "user2": [
      {
        "bookmarksId": 1,
        "title": "javascript面試常見問題",
        "url": "http://javascript面試常見問題.com.tw",
        "tags": ["javascript"]
      },
      {
        "bookmarksId": 2,
        "title": "React Hooks 詳解用法",
        "url": "http://ReactHooks詳解用法.com.tw",
        "tags": ["React"]
      }
    ]
  },
  "tags": {
    "React": [
      {
        "userId": "user1",
        "bookmarksId": 1
      },
      {
        "userId": "user1",
        "bookmarksId": 2
      },
      {
        "userId": "user2",
        "bookmarksId": 2
      }
    ],
    "Vue": [
      {
        "userId": "user1",
        "bookmarksId": 1
      }
    ],
    "javascript": [
      {
        "userId": "user2",
        "bookmarksId": 1
      }
    ],
    "ES6": [
      {
        "userId": "user1",
        "bookmarksId": 2
      }
    ]
  }
}
